jupyterlab_kishu/__init__.py
jupyterlab_kishu/_version.py
jupyterlab_kishu/handlers.py
jupyterlab_kishu/py.typed
jupyterlab_kishu-0.3.2.data/data/etc/jupyter/jupyter_server_config.d/jupyterlab_kishu.json
jupyterlab_kishu-0.3.2.data/data/share/jupyter/labextensions/jupyterlab_kishu/package.json
jupyterlab_kishu-0.3.2.data/data/share/jupyter/labextensions/jupyterlab_kishu/schemas/jupyterlab_kishu/package.json.orig
jupyterlab_kishu-0.3.2.data/data/share/jupyter/labextensions/jupyterlab_kishu/schemas/jupyterlab_kishu/plugin.json
jupyterlab_kishu-0.3.2.data/data/share/jupyter/labextensions/jupyterlab_kishu/static/747.4ac55d24323673d1f1ef.js
jupyterlab_kishu-0.3.2.data/data/share/jupyter/labextensions/jupyterlab_kishu/static/763.808ebccfa2f26b6e8d59.js
jupyterlab_kishu-0.3.2.data/data/share/jupyter/labextensions/jupyterlab_kishu/static/remoteEntry.e5a85f462356af8385f6.js
jupyterlab_kishu-0.3.2.data/data/share/jupyter/labextensions/jupyterlab_kishu/static/style.js
jupyterlab_kishu-0.3.2.data/data/share/jupyter/labextensions/jupyterlab_kishu/static/third-party-licenses.json
jupyterlab_kishu-0.3.2.data/data/share/jupyter/labextensions/jupyterlab_kishu/install.json
jupyterlab_kishu-0.3.2.dist-info/METADATA
jupyterlab_kishu-0.3.2.dist-info/WHEEL
jupyterlab_kishu-0.3.2.dist-info/RECORD
