Metadata-Version: 2.4
Name: jupyterlab_kishu
Version: 0.3.2
Dynamic: Keywords
Summary: A JupyterLab extension to interact with Kishu.
Project-URL: Homepage, https://github.com/illinoisdata/kishu
Project-URL: Bug Tracker, https://github.com/illinoisdata/kishu/issues
Project-URL: Repository, https://github.com/illinoisdata/kishu.git
Author-email: Yongjoo Park <yongjoo@g.illinois.edu>
License: Apache-2.0
Classifier: Framework :: Jupyter
Classifier: Framework :: Jupyter :: JupyterLab
Classifier: Framework :: Jupyter :: JupyterLab :: 4
Classifier: Framework :: Jupyter :: JupyterLab :: Extensions
Classifier: Framework :: Jupyter :: JupyterLab :: Extensions :: Prebuilt
Classifier: License :: OSI Approved :: Apache Software License
Classifier: Programming Language :: Python
Classifier: Programming Language :: Python :: 3
Classifier: Programming Language :: Python :: 3.8
Classifier: Programming Language :: Python :: 3.9
Classifier: Programming Language :: Python :: 3.10
Classifier: Programming Language :: Python :: 3.11
Requires-Python: >=3.8
Requires-Dist: jupyter-server
Requires-Dist: jupyterlab
Requires-Dist: kishu
Requires-Dist: tornado
Provides-Extra: dev
Requires-Dist: black; extra == 'dev'
Requires-Dist: flake8; extra == 'dev'
Requires-Dist: isort; extra == 'dev'
Requires-Dist: mypy; extra == 'dev'
Requires-Dist: pytest; extra == 'dev'
